selfusepy/__init__.py
selfusepy/jsonparse.py
selfusepy/log.py
selfusepy/utils.py
selfusepy-0.4.0.dist-info/licenses/LICENSE
selfusepy-0.4.0.dist-info/METADATA
selfusepy-0.4.0.dist-info/WHEEL
selfusepy-0.4.0.dist-info/top_level.txt
selfusepy-0.4.0.dist-info/RECORD
