Metadata-Version: 2.4
Name: selfusepy
Version: 0.4.0
Summary: Self-Use Python lib
Author-email: Luoming Xu <me@luomingxu.cn>
License-Expression: Apache-2.0
Project-URL: Homepage, https://github.com/LuomingXu/selfusepy
Project-URL: Documentation, https://github.com/LuomingXu/selfusepy
Project-URL: Repository, https://github.com/LuomingXu/selfusepy
Project-URL: Issues, https://github.com/LuomingXu/selfusepy/issues
Classifier: Development Status :: 3 - Alpha
Classifier: Intended Audience :: Customer Service
Classifier: Programming Language :: Python :: 3.10
Classifier: Programming Language :: Python :: 3.11
Classifier: Programming Language :: Python :: 3.12
Classifier: Programming Language :: Python :: 3.13
Classifier: Programming Language :: Python :: 3.14
Classifier: Natural Language :: Chinese (Simplified)
Classifier: Operating System :: OS Independent
Classifier: Topic :: Utilities
Classifier: Typing :: Typed
Requires-Python: >=3.10
License-File: LICENSE
Dynamic: license-file
